roche_aws/__init__.py
roche_aws-0.0.0.dist-info/WHEEL
roche_aws-0.0.0.dist-info/METADATA
roche_aws-0.0.0.dist-info/RECORD
