Metadata-Version: 2.1
Name: roche-aws
Version: 0.0.0
Summary: Empty roche_aws for security reasons
Author: Iwan Silvan Bolzern
Author-email: iwan.bolzern@roche.com
Requires-Python: >=3.6,<4.0
Classifier: Programming Language :: Python :: 3
Classifier: Programming Language :: Python :: 3.6
Classifier: Programming Language :: Python :: 3.7
Classifier: Programming Language :: Python :: 3.8
Classifier: Programming Language :: Python :: 3.9
